{
  "templateId":"template-001",
  "result":[
    {
      "key":"requestStatusByOrganization.chart",
      "title":"부서별 요청현황",
      "result":{
        "chartId":"requestStatusByOrganization.chart",
        "chartName":"부서별 요청현황",
        "chartType":"chart.basicColumn",
        "chartDesc":"",
        "tags":[
          {
            "tagId":"all",
            "tagValue":"전체"
          },
          {
            "tagId":"4028b21f7c90d996017c91ae7987004f",
            "tagValue":"단순의뢰"
          },
          {
            "tagId":"4028b21f7c9adb6a017c9b18489900c9",
            "tagValue":"개발의뢰"
          },
          {
            "tagId":"4028b21f7c9ff7c8017ca06bde520058",
            "tagValue":"원장변경"
          },
          {
            "tagId":"2c9180867cc31a25017cc7a779d70523",
            "tagValue":"출력의뢰"
          }
        ],
        "chartConfig":{
          "range":{
            "type":"chart.range.none",
            "from":null,
            "to":null
          },
          "operation":"count",
          "periodUnit":"M",
          "documentStatus":"only.running.document",
          "condition":null
        },
        "chartData":[
          {
            "id":"4028b21f7c90d996017c91ae7987004f",
            "category":"전체",
            "value":"2",
            "series":"단순의뢰",
            "linkKey":null
          },
          {
            "id":"4028b21f7c90d996017c91ae7987004f",
            "category":"영업본부",
            "value":"2",
            "series":"단순의뢰",
            "linkKey":"4028b2d57d37168e017d3715fae00002"
          },
          {
            "id":"4028b21f7c90d996017c91ae7987004f",
            "category":"기업 금융본부",
            "value":"1",
            "series":"단순의뢰",
            "linkKey":"4028b2d57d37168e017d3713bb430003"
          },
          {
            "id":"4028b21f7c90d996017c91ae7987004f",
            "category":"KiwiBank 사업부",
            "value":"0",
            "series":"단순의뢰",
            "linkKey":"4028b2d57d37168e017d3715fae00004"
          },
          {
            "id":"4028b21f7c90d996017c91ae7987004f",
            "category":"차세대추진단 ICT 본부",
            "value":"0",
            "series":"단순의뢰",
            "linkKey":"4028b2d57d37168e017d3715fae00004"
          },
          {
            "id":"4028b21f7c90d996017c91ae7987004f",
            "category":"여신본부",
            "value":"0",
            "series":"단순의뢰",
            "linkKey":"4028b2d57d37168e017d3715fae00004"
          },
          {
            "id":"4028b21f7c90d996017c91ae7987004f",
            "category":"리스크관리본부",
            "value":"0",
            "series":"단순의뢰",
            "linkKey":"4028b2d57d37168e017d3715fae00004"
          },
          {
            "id":"4028b21f7c90d996017c91ae7987004f",
            "category":"경영지원본부",
            "value":"0",
            "series":"단순의뢰",
            "linkKey":"4028b2d57d37168e017d3715fae00004"
          },
          {
            "id":"4028b21f7c90d996017c91ae7987004f",
            "category":"소비자보호본부",
            "value":"0",
            "series":"단순의뢰",
            "linkKey":"4028b2d57d37168e017d3715fae00004"
          },
          {
            "id":"4028b21f7c90d996017c91ae7987004f",
            "category":"준법지원부",
            "value":"0",
            "series":"단순의뢰",
            "linkKey":"4028b2d57d37168e017d3715fae00004"
          },
          {
            "id":"4028b21f7c90d996017c91ae7987004f",
            "category":"감사부",
            "value":"0",
            "series":"단순의뢰",
            "linkKey":"4028b2d57d37168e017d3715fae00004"
          },



          {
            "id":"4028b21f7c9adb6a017c9b18489900c9",
            "category":"전체",
            "value":"2",
            "series":"개발의뢰",
            "linkKey":null
          },
          {
            "id":"4028b21f7c9adb6a017c9b18489900c9",
            "category":"본부 1",
            "value":"2",
            "series":"개발의뢰",
            "linkKey":"4028b2d57d37168e017d3715fae00002"
          },
          {
            "id":"4028b21f7c9adb6a017c9b18489900c9",
            "category":"본부 2",
            "value":"0",
            "series":"개발의뢰",
            "linkKey":"4028b2d57d37168e017d3713bb430003"
          },
          {
            "id":"4028b21f7c9adb6a017c9b18489900c9",
            "category":"본부 3",
            "value":"0",
            "series":"개발의뢰",
            "linkKey":"4028b2d57d37168e017d3715fae00004"
          },
          {
            "id":"4028b21f7c9ff7c8017ca06bde520058",
            "category":"전체",
            "value":"1",
            "series":"원장변경",
            "linkKey":null
          },
          {
            "id":"4028b21f7c9ff7c8017ca06bde520058",
            "category":"본부 1",
            "value":"1",
            "series":"원장변경",
            "linkKey":"4028b2d57d37168e017d3715fae00002"
          },
          {
            "id":"4028b21f7c9ff7c8017ca06bde520058",
            "category":"본부 2",
            "value":"0",
            "series":"원장변경",
            "linkKey":"4028b2d57d37168e017d3713bb430003"
          },
          {
            "id":"4028b21f7c9ff7c8017ca06bde520058",
            "category":"본부 3",
            "value":"0",
            "series":"원장변경",
            "linkKey":"4028b2d57d37168e017d3715fae00004"
          },
          {
            "id":"2c9180867cc31a25017cc7a779d70523",
            "category":"전체",
            "value":"0",
            "series":"출력의뢰",
            "linkKey":null
          },
          {
            "id":"2c9180867cc31a25017cc7a779d70523",
            "category":"본부 1",
            "value":"0",
            "series":"출력의뢰",
            "linkKey":"4028b2d57d37168e017d3715fae00002"
          },
          {
            "id":"2c9180867cc31a25017cc7a779d70523",
            "category":"본부 2",
            "value":"0",
            "series":"출력의뢰",
            "linkKey":"4028b2d57d37168e017d3713bb430003"
          },
          {
            "id":"2c9180867cc31a25017cc7a779d70523",
            "category":"본부 3",
            "value":"0",
            "series":"출력의뢰",
            "linkKey":"4028b2d57d37168e017d3715fae00004"
          }
        ]
      }
    },
    {
      "key":"requestStatusByUser.list",
      "title":"개인 요청 현황",
      "result":[
        {
          "documentId":"4028b21f7c90d996017c91ae7987004f",
          "documentName":"단순의뢰",
          "count":0
        },
        {
          "documentId":"4028b21f7c9adb6a017c9b18489900c9",
          "documentName":"개발의뢰",
          "count":0
        },
        {
          "documentId":"4028b21f7c9ff7c8017ca06bde520058",
          "documentName":"원장변경",
          "count":0
        },
        {
          "documentId":"2c9180867cc31a25017cc7a779d70523",
          "documentName":"출력의뢰",
          "count":0
        }
      ]
    },
    {
      "key":"requestListByOrganization.list",
      "title":"요청현황",
      "result":{
        "organizationId":"",
        "organizationName":"",
        "columnTitle":[
          "순번",
          "신청부서",
          "문서 종류",
          "제목",
          "신청일시",
          "완료 희망일시",
          "상태",
          "PL",
          "신청자",
          "난이도",
          "문서번호"
        ],
        "columnWidth":[
          "60px",
          "200px",
          "200px",
          "300px",
          "150px",
          "150px",
          "150px",
          "150px",
          "150px",
          "80px",
          "300px"
        ],
        "columnType":[
          "number",
          "string",
          "string",
          "string",
          "dateTime",
          "dateTime",
          "string",
          "string",
          "string",
          "string",
          "string"
        ],
        "contents":[
          [
            "",
            "본부 1",
            "원장변경",
            "test",
            "2022-02-24T23:46:00.000Z",
            "2022-02-24T23:46:00.000Z",
            "running",
            "",
            "서비스 관리자",
            "",
            "CSR-20220224-001"
          ],
          [
            "",
            "본부 1",
            "단순의뢰",
            " 단순의뢰",
            "2022-02-24T23:46:00.000Z",
            "2022-02-24T23:46:00.000Z",
            "running",
            "",
            "서비스 관리자",
            "",
            "CSR-20220224-002"
          ],
          [
            "",
            "그룹 1-2",
            "개발의뢰",
            "개발의뢰",
            "2022-02-24T23:47:00.000Z",
            "2022-02-24T23:47:00.000Z",
            "running",
            "",
            "서비스 관리자",
            "",
            "CSR-20220224-003"
          ],
          [
            "",
            "그룹 1-2",
            "개발의뢰",
            "개발의뢰",
            "2022-02-24T23:47:00.000Z",
            "2022-02-24T23:47:00.000Z",
            "running",
            "",
            "서비스 관리자",
            "",
            "CSR-20220224-004"
          ],
          [
            "",
            "본부 2",
            "단순의뢰",
            "",
            "2022-02-25T00:01:00.000Z",
            "2022-02-25T00:01:00.000Z",
            "running",
            "",
            "업무흐름 관리자",
            "",
            "CSR-20220225-005"
          ]
        ]
      }
    }
  ]
}
